heputils/__init__.py
heputils/convert.py
heputils/plot.py
heputils/utils.py
heputils/version.py
heputils/cli/__init__.py
heputils/cli/cli.py
heputils-0.0.7.dist-info/LICENSE
heputils-0.0.7.dist-info/METADATA
heputils-0.0.7.dist-info/WHEEL
heputils-0.0.7.dist-info/entry_points.txt
heputils-0.0.7.dist-info/top_level.txt
heputils-0.0.7.dist-info/RECORD
