Metadata-Version: 2.1
Name: heputils
Version: 0.0.7
Summary: Helper utilities around the Scikit-HEP ecosystem for common tasks in HEP
Home-page: https://github.com/matthewfeickert/heputils
Author: Matthew Feickert
Author-email: matthew.feickert@cern.ch
License: BSD 3-Clause
Project-URL: Documentation, https://matthewfeickert.github.io/heputils/
Project-URL: Source, https://github.com/matthewfeickert/heputils
Project-URL: Tracker, https://github.com/matthewfeickert/heputils/issues
Keywords: hep utilities scikit-hep physics
Platform: UNKNOWN
Classifier: Development Status :: 3 - Alpha
Classifier: License :: OSI Approved :: Apache Software License
Classifier: Intended Audience :: Science/Research
Classifier: Topic :: Scientific/Engineering
Classifier: Topic :: Scientific/Engineering :: Physics
Classifier: Programming Language :: Python :: 3
Classifier: Programming Language :: Python :: 3.7
Classifier: Programming Language :: Python :: 3.8
Classifier: Programming Language :: Python :: 3.9
Requires-Python: >=3.7
License-File: LICENSE
Requires-Dist: click (>=6.0)
Requires-Dist: awkward (>=1.0)
Requires-Dist: uproot (>=4.0)
Requires-Dist: mplhep (>=0.3.8)
Requires-Dist: hist[plot] (>=2.3.0)
Requires-Dist: uproot3 (>=3.14)
Provides-Extra: complete
Requires-Dist: black ; extra == 'complete'
Requires-Dist: bump2version ; extra == 'complete'
Requires-Dist: check-manifest ; extra == 'complete'
Requires-Dist: flake8 ; extra == 'complete'
Requires-Dist: pre-commit ; extra == 'complete'
Requires-Dist: pytest-console-scripts (~=0.2) ; extra == 'complete'
Requires-Dist: pytest-cov (~=2.8) ; extra == 'complete'
Requires-Dist: pytest-mock (~=3.0) ; extra == 'complete'
Requires-Dist: pytest (~=6.0) ; extra == 'complete'
Requires-Dist: twine ; extra == 'complete'
Provides-Extra: develop
Requires-Dist: black ; extra == 'develop'
Requires-Dist: bump2version ; extra == 'develop'
Requires-Dist: check-manifest ; extra == 'develop'
Requires-Dist: flake8 ; extra == 'develop'
Requires-Dist: pre-commit ; extra == 'develop'
Requires-Dist: pytest-console-scripts (~=0.2) ; extra == 'develop'
Requires-Dist: pytest-cov (~=2.8) ; extra == 'develop'
Requires-Dist: pytest-mock (~=3.0) ; extra == 'develop'
Requires-Dist: pytest (~=6.0) ; extra == 'develop'
Requires-Dist: twine ; extra == 'develop'
Provides-Extra: lint
Requires-Dist: black ; extra == 'lint'
Requires-Dist: flake8 ; extra == 'lint'
Provides-Extra: test
Requires-Dist: check-manifest ; extra == 'test'
Requires-Dist: pytest-console-scripts (~=0.2) ; extra == 'test'
Requires-Dist: pytest-cov (~=2.8) ; extra == 'test'
Requires-Dist: pytest-mock (~=3.0) ; extra == 'test'
Requires-Dist: pytest (~=6.0) ; extra == 'test'
